[
  {
    "pages": [
      {
        "entities": [
          {
            "text": "قرارداد فی­مابین مشتری و کارگزار- قرارداد آتی",
            "contractTitle": true
          },
          {
            "text": "موضوع بند 46 ماده 1 و ماده 11 دستورالعمل معاملات قرارداد آتی در بورس اوراق بهادار تهران، مصوب مورخ 16/12/1396 هیئت­مدیره سازمان بورس و اوراق بهادار"
          },
          {
            "text": "ماده 9) مقدمه"
          },
          {
            "text": "این قرارداد بین شرکت کارگزاری به مشخصات جدول زیر که از این پس در این قرارداد \"کارگزار\" نامیده می‌شود:"
          },
          {
            "table": [
              [
                {
                  "text": "نام کارگزار: شرکت کارگزاری خبرگان سهام"
                },
                {
                  "text": "شماره ثبت:111591"
                }
              ],
              [
                {
                  "text": "تاریخ ثبت: 09/12/1373"
                },
                {
                  "text": "محل ثبت: تهران"
                }
              ],
              [
                {
                  "text": "شماره ثبت نزد سازمان بورس:10638"
                },
                {
                  "text": "شماره تلفن دفتر مرکزی:42382-021"
                }
              ],
              [
                {
                  "text": "شماره فاکس دفتر مرکزی:88782462-021"
                },
                {
                  "text": "کدپستی: 1517938314"
                }
              ],

              [
                {
                  "text": "نام، نام‌خانوادگی و سمت آخرین صاحبان امضاء مجاز:",
                  "name": [
                    "1- خانم / آقای  ناصر آقاجانی  سمت: مدیر عامل و نایب رئیس هیات مدیره",
                    "2- خانم / آقای  سیدمحسن حسینی خلیلی  سمت: رئیس هیات مدیره "
                  ],
                  "nestedItemValue": true,
                  "div": true
                },

                {
                  "text": "شماره و تاریخ روزنامه رسمی: ",
                  "name": [
                    "روزنامه رسمی شماره    22525",
                    "  مورخ    29/  04/   1401"
                  ],
                  "nestedItemValue": true,
                  "div": true
                }
              ],
              [
                {
                  "text": "آدرس دفتر مرکزی: تهران- میدان ونک- خیابان گاندی جنوبی – خیابان بیست و یکم- پلاک 7"
                }
              ]
            ],
            "id": "table"
          },

          {
            "text": "و مشتری حقیقی یا حقوقی یا وکیل/ نماینده قانونی وی به مشخصات جداول متناسب زیر که از این پس در این قرارداد\"مشتری\" نامیده می‌شود:"
          },
          {
            "text": "الف) برای اشخاص حقیقی ایرانی:",
            "title": true
          },
          {
            "table": [
              [
                {
                  "text": "نام و نام خانوادگی:",
                  "name": ["firstName","lastName"]
                },
                {
                  "text": "جنسیت:",
                  "name": "male"
                }
              ],
              [
                {
                  "text": "کدبورسی:  ",
                  "name": "bource_code"
                },
                {
                  "text": "تاریخ دریافت کد مالکیت:"
                }
              ],
              [
                {
                  "text": "نام پدر:",
                  "name": "fatherName"
                },
                {
                  "text": "تاریخ تولد (روز/ ماه/ سال):",
                  "name": "birthDate"
                }
              ],
              [
                {
                  "text": "محل تولد:",
                  "name": "birth_location"
                },
                {
                  "text": "کد ملی:",
                  "name": "nationalCode"
                }
              ],
              [
                {
                  "text": "شماره شناسنامه:",
                  "name": "birth_certificate_id"
                },
                {
                  "text": "محل صدور شناسنامه:",
                  "name": "issue_location"
                }
              ],
              [
                {
                  "text": "شماره سریال شناسنامه:",
                  "name": "birth_certificate_serial_number"
                },
                {
                  "text": "شماره تلفن منزل با کد شهر:",
                  "name": ["tel", "tel_prefix"]
                }
              ],
              [
                {
                  "text": "شماره تلفن محل ‌کار با کد شهر:",
                  "name": ["work_tel", "work_tel_prefix"]
                },
                {
                  "text": "شماره تلفن همراه:",
                  "name": "phone"
                }
              ],
              [
                {
                  "text": "نام و کد بانک:",
                  "name": ["bankName", "bankBranchCode"]
                },
                {
                  "text": "شماره حساب بانکی:",
                  "name": "bankAccountNumber"
                }
              ],
              [
                {
                  "text": "آدرس پست الکترونیکی:",
                  "name": "email"
                }
              ],
              [
                {
                  "text": "آدرس منزل:",
                  "name": "full_address"
                }
              ],
              [
                {
                  "text": "آدرس محل کار:",
                  "name": "full_work_address"
                }
              ],
              []
            ],
            "id": "table"
          }
        ]
      }
    ]
  },
  {
    "pages": [
      {
        "entities": [
          {
            "text": ""
          },
          {
            "text": "ب) برای اشخاص حقوقی ایرانی:",
            "title": true
          },
          {
            "table": [
              [
                {
                  "text": "نام:"
                },
                {
                  "text": "شماره ثبت:"
                }
              ],
              [
                {
                  "text": "تاریخ ثبت:"
                },
                {
                  "text": "محل ثبت:"
                }
              ],
              [
                {
                  "text": "کد مالکیت:"
                },
                {
                  "text": "شناسه ملی:"
                }
              ],
              [
                {
                  "text": "شماره تلفن دفتر مرکزی:"
                },
                {
                  "text": "شماره فاکس دفتر مرکزی:"
                }
              ],
              [
                {
                  "text": "نام، نام‌خانوادگی و سمت آخرین صاحبان امضاء مجاز:",
                  "name": "",
                  "itemValue": [
                    "1- خانم/آقای   :",
                    "سمت",
                    "2- خانم/آقای  :",
                    "سمت",
                    "3- خانم/آقای   :",
                    "سمت"
                  ],
                  "value": ["", "", "", "", "", ""],
                  "div": true
                }
              ],
              [
                {
                  "text": "شماره و تاریخ روزنامه رسمی:"
                },
                {
                  "text": "روزنامه رسمی شماره                   مورخ:        "
                }
              ],
              [
                {
                  "text": "نام و کد بانک:"
                },
                {
                  "text": "شماره حساب بانکی:"
                }
              ],
              [
                {
                  "text": "آدرس پست الکترونیکی:"
                }
              ],
              [
                {
                  "text": "نوع شخصیت حقوقی:"
                }
              ],
              [
                {
                  "text": "آدرس دفتر مرکزی:"
                }
              ]
            ],
            "id": "table"
          },
          {
            "text": " ج) برای اشخاص خارجی (حقیقی / حقوقی):",
            "title": true
          },
          {
            "table": [
              [
                {
                  "text": "نام:"
                },
                {
                  "text": "تابعیت:"
                }
              ],
              [
                {
                  "text": "شماره پاسپورت / شماره ثبت:"
                },
                {
                  "text": "شماره سرمایه‌گذار خارجی:"
                }
              ],
              [
                {
                  "text": "شماره تلفن محل کار / شماره تلفن دفتر مرکزی:"
                },
                {
                  "text": "نام و کد بانک:"
                }
              ],
              [
                {
                  "text": "شماره حساب بانکی:"
                },
                {
                  "text": "آدرس پست الکترونیکی:"
                }
              ],
              [
                {
                  "text": "آدرس محل کار / آدرس دفتر مرکزی در ایران:"
                }
              ],
              [
                {
                  "text": "آدرس محل کار / آدرس دفتر مرکزی در خارج از کشور:"
                }
              ]
            ],
            "id": "table"
          }
        ]
      }
    ]
  },
  {
    "pages": [
      {
        "entities": [
          {
            "text": ""
          },

          {
            "text": "د) برای وکیل / نماینده قانونی:",
            "title": true
          },
          {
            "table": [
              [
                {
                  "text": "حقیقی"
                }
              ],
              [
                {
                  "text": "نام و نام خانوادگی:"
                },
                {
                  "name": "",
                  "itemValue": ["زن", "مرد"],
                  "value": ["", ""],
                  "div": true
                }
              ],
              [
                {
                  "name": "",
                  "itemValue": [
                    "1-شماره وکالتنامه / نامه نمایندگی",
                    "۲-شماره وکالتنامه / نامه نمایندگی"
                  ],
                  "value": ["", ""],
                  "div": true
                }
              ],
              [
                {
                  "text": "نام پدر:"
                },
                {
                  "text": "تاریخ تولد (روز/ ماه/ سال):"
                }
              ],
              [
                {
                  "text": "محل تولد:"
                },
                {
                  "text": "کد ملی:"
                }
              ],
              [
                {
                  "text": "شماره شناسنامه:"
                },
                {
                  "text": "محل صدور شناسنامه:"
                }
              ],
              [
                {
                  "text": "شماره سریال شناسنامه:"
                },
                {
                  "text": "شماره تلفن منزل با کد شهر:"
                }
              ],
              [
                {
                  "text": "شماره تلفن محل ‌کار با کد شهر:"
                },
                {
                  "text": "شماره تلفن همراه:"
                }
              ],
              [
                {
                  "text": "نام و کد بانک:"
                },
                {
                  "text": "شماره حساب بانکی:"
                }
              ],
              [
                {
                  "text": "آدرس پست الکترونیکی:"
                }
              ],
              [
                {
                  "text": "آدرس منزل:"
                }
              ],
              [
                {
                  "text": "آدرس محل کار:"
                }
              ],
              [
                {
                  "text": "حقوقی"
                }
              ],
              [
                {
                  "text": "نام وکیل:"
                },
                {
                  "text": "شماره ثبت:"
                }
              ],
              [
                {
                  "text": "تاریخ ثبت:"
                },
                {
                  "text": "محل ثبت:"
                }
              ],
              [
                {
                  "text": "شماره و تاریخ وکالتنامه/ نامه نمایندگی:"
                },
                {
                  "text": "شناسه ملی:"
                }
              ],
              [
                {
                  "text": "شماره تلفن دفتر مرکزی:"
                },
                {
                  "text": "شماره فاکس دفتر مرکزی:"
                }
              ],
              [
                {
                  "text": "نام، نام‌خانوادگی و سمت آخرین صاحبان امضاء مجاز:",
                  "name": "",
                  "itemValue": [
                    "1- خانم/آقای   :",
                    "سمت",
                    "2- خانم/آقای  :",
                    "سمت",
                    "3- خانم/آقای   :",
                    "سمت"
                  ],
                  "value": ["", "", "", "", "", ""],
                  "div": true
                },
                {
                  "text": "شماره و تاریخ روزنامه رسمی:",
                  "name": "",
                  "itemValue": ["روزنامه رسمی شماره", "مورخ"],
                  "value": ["", ""],
                  "div": true
                }
              ],

              [
                {
                  "text": "نام و کد بانک:"
                },
                {
                  "text": "شماره حساب بانکی:"
                }
              ],
              [
                {
                  "text": "آدرس پست الکترونیکی:"
                }
              ],
              [
                {
                  "text": "نوع شخصیت حقوقی:"
                }
              ],
              [
                {
                  "text": "آدرس دفتر مرکزی:"
                }
              ]
            ],
            "id": "table"
          }
        ]
      }
    ]
  },

  {
    "pages": [
      {
        "entities": [
          {
            "text": ""
          },
          {
            "text": "ه) برای ولی/ قیم:",
            "title": true
          },
          {
            "table": [
              [
                {
                  "text": "نام و نام خانوادگی:"
                },
                {
                  "text": "جنسیت:",
                  "name": "",
                  "itemValue": ["زن", "مرد"],
                  "value": ["", ""],
                  "div": true
                }
              ],
              [
                {
                  "text": "شماره قیم­نامه:"
                },
                {
                  "text": "تاریخ قیم­نامه:"
                }
              ],
              [
                {
                  "text": "نام پدر:"
                },
                {
                  "text": "تاریخ تولد (روز/ ماه/ سال):"
                }
              ],
              [
                {
                  "text": "محل تولد:"
                },
                {
                  "text": "کد ملی:"
                }
              ],
              [
                {
                  "text": "شماره شناسنامه:"
                },
                {
                  "text": "محل صدور شناسنامه:"
                }
              ],
              [
                {
                  "text": "شماره سریال شناسنامه:"
                },
                {
                  "text": "شماره تلفن منزل با کد شهر:"
                }
              ],
              [
                {
                  "text": "شماره تلفن محل ‌کار با کد شهر:"
                },
                {
                  "text": "شماره تلفن همراه:"
                }
              ],
              [
                {
                  "text": "نام و کد بانک:"
                },
                {
                  "text": "شماره حساب بانکی اعلامی اداره سرپرستی دادگستری:"
                }
              ],
              [
                {
                  "text": "آدرس پست الکترونیکی:"
                }
              ],
              [
                {
                  "text": "آدرس منزل:"
                }
              ],
              [
                {
                  "text": "آدرس محل کار:"
                }
              ]
            ],
            "id": "table"
          }
        ]
      }
    ]
  },
  {
    "pages": [
      {
        "entities": [
          {
            "text": "به شرح مواد آتی منعقد گردید."
          },
          {
            "text": "در این قرارداد سازمان بورس و اوراق بهادار، اختصاراً سازمان، شرکت بورس اوراق بهادار تهران (شركت سهامي عام) اختصاراً بورس، قوانین، مصوبات هيأت وزيران، شورای عالی بورس و اوراق بهادار، سازمان و بورس، اختصاراً مقررات نامیده شده‌اند. "
          },
          {
            "text": "دستورالعمل معاملات قرارداد آتی در بورس اوراق بهادار تهران، مصوب 16/12/1396 هیئت­مدیره سازمان بورس و اوراق بهادار، در این قرارداد دستورالعمل نامیده می‌شود و تعاریف آن در این قرارداد به همان مفاهیم به­کار رفته‌اند."
          },
          {
            "text": "اتاق پایاپای، واحدی در شرکت سپرده‌گذاری مرکزی اوراق بهادار و تسویه وجوه (سهامی عام) است که بر اساس دستورالعمل، وظیفۀ انجام امور تسویه و پایاپای قرارداد آتی را بر عهده دارد."
          },
          {
            "text": "مشخصات قرارداد آتی حداقل شامل موارد مذکور در ماده 2 دستورالعمل بوده و حسب مورد توسط بورس، اتاق پایاپای ویا سازمان و براساس ضوابط دستورالعمل تعیین می­شود. بورس مشخصات قرارداد را پیش از آغاز دوره معاملاتی و تغییرات احتمالی آن را در طول دوره معاملاتی قرارداد آتی، در قالب اطلاعیه و از طریق سایت رسمی خود به اطلاع عموم می‌رساند."
          },
          {
            "text": "ماده 2) موضوع قرارداد ",
            "title": true
          },
          {
            "text": "موضوع قرارداد، ارائه خدمات زیر توسط کارگزار به مشتری است:"
          },
          {
            "text": "1. اجرای درخواست‌های اتخاذ موقعیت خرید و اتخاذ موقعیت فروش و همچنین درخواست­های تسویه نهایی و اعلام نوع تسویه در بازار معاملات قرارداد آتی؛"
          },
          {
            "text": "2. ایفای تعهدات مشتری در مقابل اتاق پایاپای و بورس."
          },
          {
            "text": ""
          },
          {
            "text": "ماده 3) مدت قرارداد",
            "title": true
          },
          {
            "text": "قرارداد از تاریخ ............../ امضا و ابلاغ قرارداد آغاز می‌شود و در صورت تحقق هر یک از موارد زیر خاتمه می‌یابد:",
            "regex": true,
            "values": []
          },
          {
            "text": "فسخ قرارداد و تسویه­حساب قطعی بین کارگزار و مشتری؛"
          },
          {
            "text": "تعلیق مجوز معاملات قرارداد آتی کارگزار بیش از 20 روز؛"
          },
          {
            "text": "لغو مجوز قرارداد آتی کارگزار یا عدم تمدید مجوز وی پس از اتمام دوره مجوز."
          },
          {
            "text": "ماده 4) مبلغ قرارداد",
            "title": true
          },
          {
            "text": "مبلغ قرارداد، صرفاً معادل کارمزدهای معامله است که کارگزار بر اساس مقررات از مشتری دریافت می‌کند."
          }
        ]
      }
    ]
  },
  {
    "pages": [
      {
        "entities": [
          {
            "text": "ماده 5) تعهدات مشتری",
            "title": true
          },
          {
            "text": "1.مشتری متعهد می­شود در صورت تغییر اطلاعات مندرج در جدول مشخصات مشتری، مراتب را در اسرع وقت به کارگزار اطلاع دهد."
          },
          {
            "text": "2.مشتری متعهد می­شود که بدون مطالعه و آگاهی از مقررات مربوط به قراردادهای آتی، هیچ­گونه سفارشی برای معامله قرارداد آتی صادر نکند. مشتری اعلام می‌کند از ریسک‌ها و مقررات حاکم بر بازار قرارداد آتی کاملاً مطلع بوده و آن­ها را پذیرفته است و از این ‌رو، بیانیه ریسک (فرم پیوست قرارداد) را تکمیل و امضا کرده است. مشتری اعلام می­دارد توانایی ارزیابی و تحمل ریسک مالی را که خرید یا فروش آتی به همراه خواهد داشت، دارد."
          },
          {
            "text": "3.مشتری باید برای انجام معاملات در بازار مشتقه، حسابی با عنوان حساب عملیاتی مشتری نزد كارگزار معرفی كند. مشتری در زمان معرفی این حساب، اجازه برداشت و انسداد آن و همچنین اجازه سایر امور لازم جهت انجام عملیات به­روزرسانی حساب‌ها را مطابق ضوابط دستورالعمل به کارگزار می‌دهد."
          },
          {
            "text": "4.كارگزار می‌تواند علاوه بر وجه تضمین اولیه، به­منظور اطمینان از ایفای تعهدات مشتری، وثایق یا تضامینی تا سقف تعیین­شده در مشخصات قرارداد از مشتری دریافت كند، بر این اساس مشتری موظف به تودیع وثایق لازم نزد کارگزار می­باشد."
          },
          {
            "text": "5.اتاق پایاپای یا کارگزار از طرف مشتری وكالت بلاعزل دارد متناسب با تغییرات، تمام یا بخشی از وجه تضمین را به عنوان اباحه تصرف در اختیار کارگزار طرف دیگر قرارداد آتی (بر حسب مورد خریدار یا فروشنده) قرار دهد و وی حق استفاده از آن را خواهد داشت تا در سررسید تسویه کند."
          },
          {
            "text": "6.پس از به‌روزرسانی حساب عملیاتی مشتری نزد کارگزار، چنانچه وجوه تضمین مربوط به موقعیت‌های باز مشتری کم‌تر از حداقل وجه تضمین باشد، مشتری موظف است بر اساس اخطاریه افزایش وجه تضمینی که کارگزار به وی به روش تعیین­شده در بند 17 ماده 6 این قرارداد ارسال می‌کند، تا ............................ ساعت پس از شروع معاملات روز بعد (حداکثر تا یک ساعت پیش از پایان جلسه معاملات روز بعد­)، وجه تضمین خود را تا سطح وجه تضمین لازم روز معاملاتی قبل افزایش داده و یا اقدام به بستن موقعیت­های باز خود تا حد جبران کسری وجوه تضمین نماید.",
            "regex": true,
            "values": []
          },
          {
            "text": "7.چنانچه مشتری، اخطاریه افزایش وجه تضمین دریافت کرده باشد و به هر دلیلی طی مهلت­ تعیین شده در بند 6 ماده 5 این قرارداد، تعهدات خود را ایفا ننماید، کارگزار باید در همان روز معاملاتی، راساً اقدام به بستن موقعیت­های باز مشتری تا حد جبران کسری وجه تضمین تا پایان جلسه معاملاتی آن روز ویا بازار جبرانی نماید. "
          },
          {
            "text": "در صورتی­که به هر دلیلی تعهدات مشتری ایفا نشود، کارگزار می­تواند از محل بستانکاری مشتری و یا وثایق وی نزد کارگزار، اقدام به تأمین و جبران تعهدات مشتری نماید. در صورت بستن موقعیت­های باز مشتری توسط کارگزار، مشتری حق هیچگونه اعتراض و ادعایی نسبت به انجام معامله مذکور و شرایط آن ندارد."
          },
          {
            "text": "8.چنانچه دارایی پایه موضوع قرارداد آتی، سهام یکی از شرکت­های پذیرفته­شده در بورس یا سبد سهام­ باشد، در صورت وقوع هر یک از موارد زیر، بورس حسب مورد قیمت تسویه روزانه، اندازه قرارداد، سقف موقعیت­های باز در سه سطح بازار، کارگزار و مشتری، تعداد سهام هر یک از ناشران موجود در سبد پایه ویا ترکیب سهام موجود در سبد پایه را تعدیل می‌کند و مشتری با علم به این موضوع اقدام به اتخاذ موقعیت باز در بازار قرارداد آتی می‌کند:"
          },
          {
            "text": "1) اقدام شرکتی ناشر سهم پایه یا هر یک از ناشران موجود در سبد مرجع (افزایش سرمایه و تقسیم سود)؛"
          },
          {
            "text": "2) تغییر ترکیب اوراق بهادار موجود در سبد مرجع."
          },
          {
            "text": "9.مشتری از سقف موقعیت‌های باز هر نماد معاملاتی در سطح کارگزار و مشتری آگاه است و با علم به این موضوع کارگزار را انتخاب و اقدام به اتخاذ موقعیت باز در بازار قرارداد آتی می‌کند."
          },
          {
            "text": "10.خسارت‌های مقرر در مشخصات قرارداد از محل حساب عملیاتی مشتری نزد كارگزار و در صورت عدم کفایت، از محل وثایق كارگزار نزد اتاق پایاپای تأمین و رأساً برداشت می‌شود. در صورت عدم کفایت وثایق، كارگزار مکلف است حسب دستور اتاق پایاپای خسارت‌های مربوطه را پرداخت كند. کارگزار می‌تواند این خسارات را رأساً از محل بستانکاری یا وثایق و تضامین مشتری نزد کارگزار برداشت کند و در صورت عدم کفایت از مشتری مطالبه نماید. مستندات این اقدامات باید در سوابق کارگزاری نگهداری شود."
          },
          {
            "text": "11. مشتری متعهد است در ارائه سفارش‌های خرید و فروش، همه قوانین و مقررات مربوطه به‌ویژه مقررات مربوط به فصل ششم قانون بازار (دارندگان اطلاعات نهانی، دست‌کاری قیمت) و مقررات مبارزه با پولشویی را رعایت کند."
          },
          {
            "text": "12. مشتری متعهد به تأدیه کارمزدهای معامله و تسویه نهایی در سررسید است."
          },
          {
            "text": "13. چنانچه تسویه به­ صورت فیزیکی باشد، از همۀ دارندگان موقعیت باز فروش در قراردادهای آتی که دارایی پایه موضوع قرارداد را به طرف مقابل تحویل می­دهند، مالیات اخذ می­شود."
          }
        ]
      }
    ]
  },
  {
    "pages": [
      {
        "entities": [
          {
            "text": "14. بورس می‌تواند در مورد تعداد کارگزارانی که یک مشتری می‌تواند از طریق آنها معامله کند، محدودیت تعیین کند. در این صورت تغییر کارگزار صرفاً با رعایت مقررات اتاق پایاپای و تکمیل فرم‌ مربوطه و تأیید آن توسط کارگزار مبدأ، کارگزار مقصد و اتاق پایاپای امکان‌پذیر است. مسئولیت تخلف از مفاد این بند و جبران خسارت‌های مربوطه بر عهده مشتری است."
          },
          {
            "text": "15. مشتری ملزم است سفارش خود را در فرم‌های تعیین­شده توسط بورس، تکمیل و ارائه کند."
          },
          {
            "text": "16. مشتری با امضای این قرارداد، همه مقررات و مفاد دستورالعمل و اصلاحات بعدی آن را می‌پذیرد و متعهد به ایفای تمام وظایف و تعهدات خود مطابق قرارداد و مقررات است، هر چند در این قرارداد ذکر نشده باشد."
          },
          {
            "text": "17.در صورت تعیین سایر روش‌های تخصیص غیر از روش ردگیری موقعیت، اتاق پایاپای از طرف دارندگان موقعیت باز در نماد معاملاتی قراردادهای آتی وکالت دارد تا مشتری طرف قرارداد آنان یا هر دارنده موقعیت باز در آن نماد را برای تسویه نهایی به آنان حواله دهد."
          },
          {
            "text": "18. در همه مواردی که مشتری ملزم به واریز وجه به حساب کارگزار است، مبالغ باید به شماره حساب جاری.......................... نزد بانک عامل ............................ شعبه ...................... بابت معاملات قرارداد آتی به نام کارگزار واریز شود و رسید واریز وجه به شماره .......................... فکس و تصویر اسکن­شده آن به آدرس .................................... ایمیل شود.",
            "regex": true,
            "values": []
          },
          {
            "text": "ماده 6) تعهدات کارگزار",
            "title": true
          },
          {
            "text": "1.نماینده کارگزار جهت اجرای مفاد این قرارداد و ارتباط با مشتری، آقای/خانم .................. است. تکمیل و امضای سایر مدارک توسط نماینده برای کارگزار تعهدآور است.",
            "regex": true,
            "values": []
          },
          {
            "text": "2.کارگزار مسئولیت ایفای تعهدات مشتریان در مقابل اتاق پایاپای را مطابق ضوابط دستورالعمل بر عهده دارد. بدیهی است که مسئولیت کارگزار، رافع تعهدات مشتری در مقابل کارگزار نمی‌باشد."
          },
          {
            "text": "3.كارگزار باید سفارش مشتریان را در فرم‌های تعیین­شده توسط بورس ثبت و نگهداری کند."
          },
          {
            "text": "4.كارگزار باید فرم‌های ثبت سفارش را برای هر مشتری به ترتیب شماره سریال، بایگانی كند و حسب درخواست به بورس یا سازمان ارائه نماید. جهت رعایت نوبت مشتریان ثبت تاریخ و زمان دقیق تكمیل فرم سفارش الزامی است."
          },
          {
            "text": "5.کارگزار موظف است شماره حساب جاری خود نزد بانک عامل را که مطابق فرم اعلام حساب در اختیار، افتتاح آن را به اطلاع بورس و شرکت سپرده‌گذاری مرکزی اوراق بهادار و تسویه وجوه رسانده است، در بند 18 ماده 5 این قرارداد مرقوم کند."
          },
          {
            "text": "6.کارگزار موظف است پیش ازآغاز معاملات، رویه­ها و سازوکارهای اجرایی، قوانین و مقررات و ریسک­های موجود در بازار را به اطلاع مشتری رسانده و از آگاهی و دانش مشتری نسبت به موضوعات فوق اطمینان حاصل کند. اطلاع­رسانی در خصوص تغییرات موارد یاد شده بر عهده کارگزار نمی­باشد."
          },
          {
            "text": "7.کارگزار باید در زمان اخذ سفارش خرید یا فروش، وجوه تضمین موردنیاز به­علاوۀ هزینه‌های معاملاتی را به حساب عملیاتی مشتری نزد کارگزار منظور کند. موجودی حساب عملیاتی مشتری نزد کارگزار حسب الزام بورس و یا سازمان از محل وجوه واریزی وی به حساب کارگزار، بستانکاری وی در دفاتر کارگزاری و وجوه متعلق به کارگزار، قابل تأمین است."
          },
          {
            "text": "8.کارگزار موظف است در دفاتر خود برای هر مشتری و نماد معاملاتی، سرفصل‌های جداگانه‌ای ایجاد کند و در زمان اجرای سفارش‌های مشتری از کفایت وجه تضمین اولیه به­علاوۀ هزینه­های معاملاتی در حساب عملیاتی مشتری نزد کارگزار اطمینان یابد."
          },
          {
            "text": "9.كارگزار باید سوابق معاملات و صورت‌حساب مشتری را به نحوی نگه‌داری کند که حسب مورد به سازمان، بورس یا شرکت سپرده‌گذاری قابل ارائه باشد."
          },
          {
            "text": "10.در صورتی‌که مشتری پس از ارائه سفارش و قبل از انجام معامله در چهارچوب مقررات از اجرای سفارش منصرف شود یا کارگزار به هر علت نتواند نسبت به اجرای سفارش مشتری اقدام کند، حسب درخواست مشتری وجوه وی باید توسط کارگزار مسترد شود."
          },
          {
            "text": "11.كارگزار موظف است به ‌منظور پوشش تعهدات خود در قبال اتاق پایاپای، وثیقه­ای را حسب درخواست اتاق پایاپای نزد اتاق پایاپای تودیع كند. ارزش، نوع و ترکیب وثایق مورد قبول و ضوابط تعیین و اخذ آن، توسط اتاق پایاپای تعیین می­شود."
          },
          {
            "text": "12.چنانچه بر اساس شرایط بازار و به تشخیص اتاق پایاپای، وثایق تودیع­شده موضوع بند 11 ماده 6 این قرارداد از کفایت لازم برخوردار نباشد، اتاق پایاپای می­تواند از کارگزار درخواست افزایش وثیقه کند. در این حالت از اخذ موقعیت­های جدید در آن کارگزاری جلوگیری به عمل خواهد آمد و کارگزار موظف است وثیقه مورد نیاز را طی مهلت تعیین­شده نزد اتاق پایاپای تودیع کند. در صورتی­که کارگزار اقدامات لازم جهت افزایش وثایق نزد اتاق پایاپای را انجام ندهد، موضوع به مراجع رسیدگی مربوطه ارجاع می­شود."
          }
        ]
      }
    ]
  },
  {
    "pages": [
      {
        "entities": [
          {
            "text": "13.کارگزار موظف است در صورت دریافت وجه تضمین اولیه و هزینه­های معاملاتی از مشتری و نیز حسب مورد وثایق تعیین­شده توسط کارگزار، سفارش وی را در سامانه معاملات بازار قراردادهای آتی ثبت کند و مجاز نیست به هیچ وجه از وجوه مشتریان به نفع خود یا سایر اشخاص استفاده نمایند."
          },
          {
            "text": "14.کارگزار موظف است در فرآیند تسویه و پایاپای روزانه قراردادهای آتی، پس از پایان جلسه معاملات و نیز پس از دریافت گزارش اتاق پایاپای، خالص بستانکاری یا بدهکاری مشتریان خود را مطابق با مفاد ماده 24 دستورالعمل و با در نظر گرفتن هزینه­های معاملاتی و کسورات قانونی محاسبه و به حساب عملیاتی مشتری نزد کارگزار منظور کند."
          },
          {
            "text": "15.کارگزار موظف است پس از اعلام قیمت تسویه روزانه و دریافت گزارش اتاق پایاپای، در همان روز معاملاتی تا زمان اعلام­شده توسط اتاق پایاپای، گزارشی را که حداقل مشتمل بر موارد زیر است، به اطلاع اتاق پایاپای برساند:"
          },
          {
            "text": "1) موقعیت­های باز كارگزار به تفكیك مشتری و نماد معاملاتی؛"
          },
          {
            "text": "2) مانده وجوه تضمین در حساب عملیاتی هر مشتری نزد کارگزار و کفایت آن جهت پوشش حداقل وجوه تضمین."
          },
          {
            "text": "16.اگر پس از انجام عملیات بندهای 14 و 15 ماده 6 این قرارداد و یا لحاظ­شدن وجه تضمین اضافی محاسبه­شده توسط اتاق پایاپای در وجوه تضمین اولیه و لازم، موجودی حساب عملیاتی مشتری نزد کارگزار از حداقل وجه تضمین کمتر شود، کارگزار باید اخطاریه افزایش وجه تضمین را به روش تعیین­شده در بند 17 ماده 6 این قرارداد و حداکثر تا پیش از آغاز جلسۀ معاملاتی روز بعد، برای مشتری ارسال ‌کند."
          },
          {
            "text": "17.  شیوه ابلاغ اخطاریه افزایش وجه تضمین به مشتری به یکی از روش‌های زیر است:"
          },
          {
            "text": "1) حضوری و اخذ امضاي مشتري؛"
          },
          {
            "text": "2) ارسال فاکس به شماره...............................، ارسال پیامک به شماره ......................... و پست الکترونیکی به آدرس ................................",
            "regex": true,
            "values":[],
            "names":["", "phone", "email"]
          },
          {
            "text": "18.کارگزار موظف است چنانچه مشتری اخطاریه افزایش وجه تضمین دریافت کرده­است، تا پیش از واریز وجوه تضمین جبرانی یا بستن موقعیت‌های باز توسط مشتری تا حد جبران کسری وجوه تضمین، از پذیرش سفارش‌های فزاینده موقعیت‌های باز مشتری خودداری نماید. به عبارت دیگر افزایش موقعیت‌های باز برای مشتریانی که اخطاریه افزایش وجه تضمین دریافت کرده‌­اند، پس از پرداخت وجه تضمین جبرانی یا بستن موقعیت‌های باز تا حد جبران کسری وجوه تضمین امکان‌پذیر است."
          },
          {
            "text": "19.اگر مشتری تا ................................... ساعت پس از شروع معاملات روز بعد (حداکثر تا یک ساعت پیش از پایان جلسه معاملات روز بعد­)، وجه تضمین خود را تا وجه تضمین لازم روز معاملاتی قبل افزایش ندهد یا اقدام به بستن موقعیت­های باز خود تا حد جبران کسری وجه تضمین ننماید، کارگزار موظف است در همان روز معاملاتی، راساً اقدام به بستن موقعیت­های باز خود تا حد جبران کسری وجه تضمین بکند. در صورت بستن موقعیت توسط کارگزار، قرارداد آتی بر اساس قیمت معامله‌‌ای که منجر به بستن موقعیت شده­‌است، تسویه می‌شود."
          },
          {
            "text": "20.اگر بستن موقعیت‌های باز مربوطه علی­رغم ورود سفارش با قیمت بازار توسط کارگزار امکان‌پذیر نباشد، کارگزار باید حداکثر تا نیم­ساعت بعد از پایان جلسه معاملات، فهرست موقعیت‌های باز مربوطه را به اتاق پایاپای و بورس اعلام و با هماهنگی بورس در بازار جبرانی نسبت به بستن موقعیت‌ها اقدام ‌کند. اجرای بازار جبرانی منوط به فراهم­شدن امکانات فنی مورد نیاز است."
          },
          {
            "text": "21.کارگزار باید مازاد موجودی حساب عملیاتی مشتری نزد کارگزار نسبت به وجه تضمین لازم تعیین­شده را در صورت درخواست مشتری به حساب بستانکاری مشتری منظور و حداکثر ظرف ....................... پس از درخواست مشتری از طریق ......................   به وی پرداخت کند.",
            "regex": true,
            "values": []
          },
          {
            "text": "22. مشتری می‌تواند پس از پایان جلسه معاملات، تا انتهای روز کاری از کارگزار درخواست کند تا اطلاعات موقعیت‌های باز وی را به لحاظ تغییرات وجه تضمین، سود (زیان) روزانه و سایر موارد به وی ارائه کند و کارگزار موظف است پیش از شروع جلسه معاملات روز کاری بعد، اطلاعات درخواستی را در اختیار مشتری قرار دهد."
          },
          {
            "text": "23.کارگزار موظف است بنا به درخواست مشتری، گزارش کاملی از ریز معاملات انجام­شده مشتری و وضعیت حساب وی را به یکی از روش­های مندرج در بند 17 ماده 6 این قرارداد ارائه نماید."
          },
          {
            "text": "24. اگر از تأخیر یا عدم اقدام کارگزار در ایفای تعهدات موضوع دستورالعمل در مقابل اتاق پایاپای، خسارتی به مشتری وارد شود یا مشتری متحمل هزینه‌هایی شود، کارگزار ملزم به جبران همه هزینه‌ها و خسارات وارده است."
          },
          {
            "text": "25. کارگزار موظف است نسبت به حفظ و عدم افشای اطلاعات سفارش­ها و معاملات مشتری مطابق مقررات، تمهیدات لازم را به­کار برد."
          }
        ]
      }
    ]
  },
  {
    "pages": [
      {
        "entities": [
          {
            "text": "ماده 7) تسویه نهایی قرارداد آتی",
            "title": true
          },
          {
            "text": "1.تمامی دارندگان موقعیت باز اعم از خرید و فروش در صورت تمایل می­توانند در زمان تعیین اولویت نوع تسویه و در مهلت مقرر در مشخصات قرارداد، اولویت خود برای تسویه فیزیکی یا تسویه نقدی را به روش .................................... به کارگزار مربوطه اعلام کنند. در صورت عدم اعلام نوع تسویه توسط مشتری، نوع تسویه توسط اتاق پایاپای به صورت نقدی تعیین می‌شود.",
            "regex": true,
            "values": []
          },
          {
            "text": "2.اعلام موافقت با تسویه نقدی، دال بر اجرای نهایی نوع تسویه انتخاب­شده نمی­باشد."
          },
          {
            "text": "3.نوع تسویه درخواستی مشتری، پس از ارسال آن توسط کارگزار به اتاق پایاپای، قابل اصلاح یا لغو نیست."
          },
          {
            "text": "4.کارگزار باید در زمان تسویه نقدی و در مهلت تعیین­شده در مشخصات قرارداد، موارد زیر را به تفکیک مشتری در هر نماد معاملاتی و برای تمامی موقعیت­های باز (اعم از خرید و فروش) به اتاق پایاپای اعلام کند. اعلام کارگزار مبنای تخصیص وجوه موجود در حساب اعمال کارگزار به تفکیک مشتری است:"
          },
          {
            "text": "1) اعلام تعداد موقعیت­های باز برای تسویه نقدی؛"
          },
          {
            "text": "2) اعلام موافقت با تسویه نقدی به کسری از اندازه قرارداد، حسب اعلام در مشخصات قرارداد."
          },
          {
            "text": "5.در زمان تسویه نقدی، آن دسته از قراردادهای آتی قابل تسویه نقدی می­باشند که دارندگان آنها حسب مورد، ارزش مابه­التفاوت آخرین قیمت تسویه روزانه اعلامی و قیمت مبنای دارایی پایه به­علاوه هزینه­های تسویه نهایی را تأمین کرده باشند."
          },
          {
            "text": "6.آن دسته از موقعیت‌های باز با اولویت تسویه نقدی که امکان تسویه نقدی ندارند، مشمول تسویه فیزیکی می‌شوند. همچنین موقعیت‌های باز جدید اخذشده پس از زمان تعیین اولویت نوع تسویه، مشمول تسویه‌ی فیزیکی می­شوند."
          },
          {
            "text": "7.انجام فرآیند تسویه فیزیکی قرارداد آتی برای دارندۀ موقعیت باز خرید، مستلزم تأمین ارزش بازار قرارداد آتی به­علاوه هزینه­های تسویه نهایی و انجام فرآیند تسویه فیزیکی قرارداد آتی برای دارندۀ موقعیت باز فروش، مستلزم وجود دارایی پایه متناسب با موقعیت­های باز در کد مالکیت دارندۀ موقعیت باز فروش به­علاوه هزینه­های تسویه نهایی، در زمان مشخص­شده در مشخصات قرارداد می­باشد."
          },
          {
            "text": "8.کارگزار باید در زمان مشخص­شده ..........................، تعهدات مربوط به تسویه نهایی دارندگان موقعیت باز تخصیص­یافته را به اطلاع ایشان برساند. شیوه ابلاغ به مشتری به یکی از روش‌های زیر است:"
          },
          {
            "text": "1) حضوری و اخذ امضاي مشتري؛"
          },
          {
            "text": "2) ارسال فاکس به شماره .............................، ارسال پیامک به شماره .................... و پست الکترونیکی به آدرس ...............................",
            "regex": true,
            "values": ["09123345678", "test2", "hoseinkhanbeigi@gmail.com"]
          },
          {
            "text": "9.چنانچه دارایی پایه موضوع قرارداد آتی از نوع سبد باشد، اگر تمام یا بخشی از اوراق بهادار موجود در سبد پایه تعهدشده در کد معاملاتی فروشنده وجود نداشته باشد، آن قرارداد آتی قابل تسویه فیزیکی نمی­باشد."
          },
          {
            "text": "10.قراردادهای آتی­ای که قابل تسویه فیزیکی نمی­باشند، نکول در ایفای تعهدات محسوب شده و بر اساس قیمت مبنای دارایی پایه در زمان تسویه فیزیکی، تسویۀ نقدی می‌شوند. کارگزار متناسب با موقعیت‌های باز مشتریان خود که تسویۀ نقدی شده­است، مشمول خسارت‌های مقرر در مشخصات قرارداد می‌شود."
          },
          {
            "text": "11.در صورت عدم ایفای تعهدات دارندگان موقعیت باز در تسویه نهایی، خسارات مربوطه از وجوه مشتری نزد کارگزار کسر شده و در صورت عدم کفایت این وجوه، جبران مابه­التفاوت بر عهده کارگزار می­باشد."
          },
          {
            "text": "12.کارگزار موظف است پس از اعلام فهرست نهایی موقعیت‌های تخصیص­یافته به تفکیک مشتری در هر نماد معاملاتی از طرف اتاق پایاپای، در مهلت مقرر در مشخصات قرارداد، وجوه تسویه متناظر را حسب مورد از حساب کارگزار به حساب عملیاتی مشتری نزد کارگزار منظور کند."
          },
          {
            "text": "13.در صورت توقف نماد معاملاتی دارایی پایه در زمان تسویه نقدی یا تسویه فیزیکی، تسویه نهایی قرارداد آتی به روش زیر صورت می­گیرد:"
          },
          {
            "text": "الف) در زمان تسویه نقدی، بر اساس آخرین قیمت تسویه روزانه، تسویۀ نقدی می‌شود؛"
          },
          {
            "text": "ب) در زمان تسویه فیزیکی، برای قراردادهای آتی­ای که دارندگان موقعیت باز خرید، ارزش بازار آن قراردادها را تأمین نموده و دارندگان موقعیت باز فروش نیز دارایی پایه موضوع قرارداد را در کد مالکیتی خود دارا باشند، بر اساس روش تخصیص اعلامی در مشخصات قرارداد، تسویه به صورت فیزیکی انجام شده و مابقی موقعیت­های تخصیص­یافته بر اساس آخرین قیمت مبنای دارایی پایه در زمان تسویه فیزیکی، تسویۀ نقدی می‌شود."
          },
          {
            "text": "14.درصورتی­که دارایی پایه قرارداد آتی از نوع سبد سهام باشد، اگر حداقل نماد یکی از سهام موجود در سبد پایه تا پایان جلسه معاملات آخرین روز معاملاتی، متوقف باشد، قرارداد آتی بر اساس آخرین قیمت پایانی در بازار نقد، تسویه نقدی می‌شود."
          }
        ]
      }
    ]
  },

  {
    "pages": [
      {
        "entities": [
          {
            "text": "15.چنانچه دارایی پایه قرارداد آتی از نوع سبد سهام باشد، در صورتی­که اثر اقدام شرکتی بر روی سهامی که نماد آن‌ها متوقف است لحاظ شود، طبق بند (1-ب) ماده 33 دستورالعمل، تعدیلات لازم بر روی سبد پایه اعمال می‌شود و تسویه‌ی نقدی قرارداد نیز بر اساس قیمت تعدیل­شده‌ی پایانی صورت می‌گیرد."
          },
          {
            "text": "16.در صورتی­که پس از تسویه فیزیکی، میزان مالکیت دارنده دارایی پایه از سقف­های مجاز تعیین­شده در آن دارایی پایه بیشتر گردد، دارنده موظف به عرضه مازاد ایجادشده به علت تسویه فیزیکی، در مهلت تعیین­شده توسط بورس می­باشد."
          },
          {
            "text": "ماده 8) حوادث ناگهانی و فورس­ماژور",
            "title": true
          },
          {
            "text": "هرگاه اجرای تمام یا بخشی از قرارداد به واسطه یک علت خارجی، غیرقابل­پیشگیری، مقاومت‌ناپذیر و غیرقابل پیش‌بینی غیرممکن شود یا به تأخیر افتد، طرفی که در این وضعیت قرار گرفته است مسئول جبران خسارات ناشی از عدم اجرا یا تاخیر در اجرای قرارداد نیست. در این صورت وی مکلف است در اسرع وقت (حداکثر 7 روز کاری) مراتب را کتباً به طرف مقابل، بورس و سپرده­گذاری اطلاع دهد."
          },
          {
            "text": "اعلام رسمي بورس يا شركت سپرده­گذاري مركزي اوراق بهادار و تسویه وجوه در حكم اطلاع مشتري است."
          },
          {
            "text": "ماده 9) فسخ قرارداد ",
            "title": true
          },
          {
            "text": "در صورت تحقق هر یک از موارد ذیل، قرارداد از جانب هر یک از طرفین با ذکر دلایل و مستندات به شرکت سپرده­گذاری مرکزی اوراق بهادار و تسویه وجوه قابل فسخ است:"
          },
          {
            "text": "1)نقض هر یک از شروط قرارداد"
          },
          {
            "text": "2)بروز حوادث موضوع ماده 8 و تداوم آن بیش از بیست روز کاری"
          },
          {
            "text": "3)......"
          },
          {
            "text": "تبصره 1: فسخ قرارداد از ناحیه کارگزار، با اخذ مجوز/تأیید کتبی از ناحیه شرکت سپرده­گذاری مبنی بر تسویه کامل حساب ناشی از معاملات مربوط به قرارداد آتی مشتری صورت می­پذیرد. کارگزار باید مراتب فسخ را ظرف سه روز کاری از تاریخ فسخ، به اطلاع مشتری و بورس برساند."
          },
          {
            "text": "تبصره 2: در صورت فسخ قرارداد از ناحیه مشتری، کارگزار موظف است (همزمان) مراتب را به اطلاع بورس برساند و ظرف حداکثر پنج روز کاری از زمان اعلام کتبی مراتب فسخ، نسبت به تسویه کامل حساب ناشی از معاملات مربوط به قرارداد آتی مشتری اقدام نماید."
          },
          {
            "text": "تبصره 3: فسخ قرارداد مانع مطالبه هزینه‌ها و خسارات مقرر در قرارداد نیست."
          },
          {
            "text": "ماده 10) حل اختلافات ",
            "title": true
          },
          {
            "text": "در صورت بروز اختلاف در تفسیر یا اجرای مفاد تمام یا بخشی از قرارداد، طرفین بدواً سعی خواهند کرد که آن را از طریق مذاکره حل­و­فصل کنند. در صورت عدم حصول نتیجه، ترتیبات مواد 36 و 37 قانون بازار اوراق بهادار در مورد حل اختلاف لازم‌الاجرا است."
          },
          {
            "text": "ماده 11) اقامتگاه قانونی طرفین ",
            "title": true
          },
          {
            "text": "اقامتگاه طرفین همان است که در ماده یک قرارداد ذکر شده است. هر یک از طرفین در صورت تغییر نشانی موظف است اقامتگاه جدید خود را ظرف مدت حداکثر 7 روز کاری پس از تغییر به طرف دیگر اطلاع دهد. تا زمانی که نشانی جدید اعلام نشده است، مکاتبات به آدرس قبلی ارسال می‌شوند و دریافت­شده تلقی می‌شوند. "
          },
          {
            "text": "ماده 12) تغییر قرارداد",
            "title": true
          },
          {
            "text": "هرگونه تغییر در مفاد قرارداد حاضر و نیز حذف ویا اضافه نمودن شرایط و توافقات جدید به آن، باید با اطلاع و تأیید کتبی بورس صورت پذیرد. در صورتی­که در مقررات و دستورالعمل­های موجود در زمان انعقاد قرارداد حاضر، تغییراتی حاصل شود که تغییر در شرایط و مفاد قرارداد حاضر را ایجاب نماید، تغییرات مذکور، بدون نیاز به توافق ثانوی، جزء لاینفک این قرارداد خواهد بود."
          },

          {
            "text": "این قرارداد در 12 ماده و 3 تبصره، در سه نسخه تنظیم شد و در تاریخ ............... به امضای طرفین رسید. یک نسخه از قرارداد نزد طرفین خواهد بود و نسخه دیگر به بورس ارائه می‌شود.",
            "regex": true,
            "names": ["current_date"],
            "values": []
          }
        ]
      }
    ]
  }

]
